wildberries_api_client/__init__.py
wildberries_api_client/_api_client.py
wildberries_api_client/_configuration.py
wildberries_api_client/_swagger_doc/swagger_analytics.yaml
wildberries_api_client/_swagger_doc/swagger_chats.yaml
wildberries_api_client/_swagger_doc/swagger_communications.yaml
wildberries_api_client/_swagger_doc/swagger_finances.yaml
wildberries_api_client/_swagger_doc/swagger_orders_dbs.yaml
wildberries_api_client/_swagger_doc/swagger_orders_fbs.yaml
wildberries_api_client/_swagger_doc/swagger_orders_fbw.yaml
wildberries_api_client/_swagger_doc/swagger_pickup.yaml
wildberries_api_client/_swagger_doc/swagger_products.yaml
wildberries_api_client/_swagger_doc/swagger_promotion.yaml
wildberries_api_client/_swagger_doc/swagger_reports.yaml
wildberries_api_client/_swagger_doc/swagger_returns.yaml
wildberries_api_client/_swagger_doc/swagger_supplies.yaml
wildberries_api_client/_swagger_doc/swagger_tariffs.yaml
wildberries_api_client/_swagger_doc/swagger_wbd.yaml
wildberries_api_client/_swagger_doc/transliterate_script.py
wildberries_api_client/analytics/__init__.py
wildberries_api_client/analytics/api/__init__.py
wildberries_api_client/analytics/api/analitika_prodavca_csv_api.py
wildberries_api_client/analytics/api/istoria_ostatkov_api.py
wildberries_api_client/analytics/api/poiskovye_zaprosy_api.py
wildberries_api_client/analytics/api/statistika_po_prodviheniu_api.py
wildberries_api_client/analytics/api/voronka_prodah_api.py
wildberries_api_client/analytics/api_client.py
wildberries_api_client/analytics/configuration.py
wildberries_api_client/analytics/models/__init__.py
wildberries_api_client/analytics/models/all_of_stocks_report_req_params.py
wildberries_api_client/analytics/models/all_of_table_group_item_st_metrics.py
wildberries_api_client/analytics/models/all_of_table_office_item_metrics.py
wildberries_api_client/analytics/models/all_of_table_product_item_st_metrics.py
wildberries_api_client-0.3.1.dist-info/METADATA
wildberries_api_client-0.3.1.dist-info/WHEEL
wildberries_api_client-0.3.1.dist-info/RECORD
